setup.py
docs/HISTORY.txt
docs/INSTALL.txt
docs/LICENSE.GPL
docs/LICENSE.txt
iqpp/__init__.py
iqpp.rating.egg-info/PKG-INFO
iqpp.rating.egg-info/SOURCES.txt
iqpp.rating.egg-info/dependency_links.txt
iqpp.rating.egg-info/entry_points.txt
iqpp.rating.egg-info/namespace_packages.txt
iqpp.rating.egg-info/not-zip-safe
iqpp.rating.egg-info/paster_plugins.txt
iqpp.rating.egg-info/top_level.txt
iqpp/rating/README.txt
iqpp/rating/__init__.py
iqpp/rating/catalog.py
iqpp/rating/config.py
iqpp/rating/configure.zcml
iqpp/rating/events.py
iqpp/rating/interfaces.py
iqpp/rating/profiles.zcml
iqpp/rating/setuphandlers.py
iqpp/rating/utils.py
iqpp/rating/version.txt
iqpp/rating/adapters/__init__.py
iqpp/rating/adapters/configure.zcml
iqpp/rating/adapters/options.py
iqpp/rating/adapters/rating.py
iqpp/rating/content/__init__.py
iqpp/rating/content/definition.py
iqpp/rating/content/rating.py
iqpp/rating/profiles/default/catalog.xml
iqpp/rating/profiles/default/import_steps.xml
iqpp/rating/tests/__init__.py
iqpp/rating/tests/base.py
iqpp/rating/tests/test_adapter_options.py
iqpp/rating/tests/test_adapter_rating.py
iqpp/rating/tests/test_definition.py
iqpp/rating/tests/test_rating.py
iqpp/rating/tests/test_rating_manager.py
iqpp/rating/tests/utils.py
