Metadata-Version: 1.0
Name: iqpp.rating
Version: 2.0-rc2
Summary: Enables rating for arbitrary objects.
Home-page: http://iqpp.de
Author: Kai Diefenbach
Author-email: usenet@diefenba.ch
License: GPL
Keywords: rating
Platform: UNKNOWN
Classifier: Framework :: Zope2
Classifier: Framework :: Zope3
Classifier: Programming Language :: Python
Classifier: Topic :: Software Development :: Libraries :: Python Modules
